py_cdrive_api/__init__.py
py_cdrive_api/client.py
py_cdrive_api-0.0.11.dist-info/LICENSE
py_cdrive_api-0.0.11.dist-info/METADATA
py_cdrive_api-0.0.11.dist-info/WHEEL
py_cdrive_api-0.0.11.dist-info/top_level.txt
py_cdrive_api-0.0.11.dist-info/RECORD
