Metadata-Version: 2.1
Name: py-cdrive-api
Version: 0.0.11
Summary: Python API for CDrive
Home-page: https://github.com/columbustech/py-cdrive-api
Author: ColumbusTech
Author-email: columbustechio@gmail.com
License: UNKNOWN
Platform: UNKNOWN
Classifier: Programming Language :: Python :: 3
Classifier: License :: OSI Approved :: BSD License
Classifier: Operating System :: OS Independent
Requires-Python: >=3.6
Requires-Dist: requests
